setup.py
nanoplayboard/__init__.py
nanoplayboard/nano_constants.py
nanoplayboard/nano_pymata_core.py
nanoplayboard/nanoplayboard.py
nanoplayboard.egg-info/PKG-INFO
nanoplayboard.egg-info/SOURCES.txt
nanoplayboard.egg-info/dependency_links.txt
nanoplayboard.egg-info/not-zip-safe
nanoplayboard.egg-info/requires.txt
nanoplayboard.egg-info/top_level.txt