Metadata-Version: 1.0
Name: nanoplayboard
Version: 0.0.1
Summary: A Python Library for NanoPlayBoard Firmata
Home-page: https://github.com/josejuansanchez/NanoPlayBoard-Python-Library
Author: Antonio Morales and Jose Juan Sanchez
Author-email: josejuan.sanchez@gmail.com
License: GNU General Public License v3 (GPLv3)
Keywords: NanoPlayBoard,Arduino,Firmata
Platform: UNKNOWN
